archbuilder/__main__.py
builder/__init__.py
builder/builder.py
template/__init__.py
template/template.py
archbuilder-0.1.3.dist-info/METADATA
archbuilder-0.1.3.dist-info/WHEEL
archbuilder-0.1.3.dist-info/entry_points.txt
archbuilder-0.1.3.dist-info/top_level.txt
archbuilder-0.1.3.dist-info/RECORD
