Metadata-Version: 2.1
Name: archbuilder
Version: 0.1.3
Summary: A tool to enable developers set up their projects quickly
Author-email: "Coleman A. Matey" <colemanmatey@icloud.com>
Classifier: Programming Language :: Python :: 3
Requires-Python: >=3.7
